<GetEventResponse xmlns:i="http://www.w3.org/2001/XMLSchema-instance" xmlns="http://schemas.datacontract.org/2004/07/CitySpark.Portal.Models"><events xmlns:d2p1="http://schemas.datacontract.org/2004/07/CitySpark.Portal.Framework.EventModels"><d2p1:jsEvent><d2p1:Address>1465 Stringtown Road</d2p1:Address><d2p1:AllDay>false</d2p1:AllDay><d2p1:BiasTags xmlns:d4p1="http://schemas.microsoft.com/2003/10/Serialization/Arrays" i:nil="true" /><d2p1:CityState>Midway, UT</d2p1:CityState><d2p1:Date>2016-10-01T00:00:00Z</d2p1:Date><d2p1:DateEnd>2016-10-01T13:00:00Z</d2p1:DateEnd><d2p1:DateStart>2016-10-01T07:30:00Z</d2p1:DateStart><d2p1:Description>Test your mettle in a race with thunder. Reserved for a brave few, it's 12 kilometers of willpower vs horsepower. From the Dam to the Station, along the scenic route of the Heber Valley Railroad, you will write the next chapter in the iconic story of Man and Machine. 

___
Will you make it back to the platform before the Mighty Train? There's only one way to find out.</d2p1:Description><d2p1:Distance>28.5</d2p1:Distance><d2p1:Free>false</d2p1:Free><d2p1:HasTime>true</d2p1:HasTime><d2p1:Id>ff4b16823b7d435cbf2797fa42ea53bd</d2p1:Id><d2p1:Images><d2p1:jsImg><d2p1:id>1</d2p1:id><d2p1:url>https://citysparkstorage.blob.core.windows.net/portalimages/portalimages/4f8e0bc0-d96a-45df-9df8-751802b8a595.large.png</d2p1:url></d2p1:jsImg></d2p1:Images><d2p1:IsPromotion>false</d2p1:IsPromotion><d2p1:Labels xmlns:d4p1="http://schemas.microsoft.com/2003/10/Serialization/Arrays" /><d2p1:Links /><d2p1:Media i:nil="true" /><d2p1:MediumImg>https://citysparkstorage.blob.core.windows.net/portalimages/portalimages/4f8e0bc0-d96a-45df-9df8-751802b8a595.medium.png</d2p1:MediumImg><d2p1:Name>The Dam Train Race</d2p1:Name><d2p1:Occurances i:nil="true" /><d2p1:PId>2770890</d2p1:PId><d2p1:Picked>false</d2p1:Picked><d2p1:PopularityIndex>13</d2p1:PopularityIndex><d2p1:Price>30</d2p1:Price><d2p1:PriceHigh>50</d2p1:PriceHigh><d2p1:PriceText i:nil="true" /><d2p1:SmallImg>https://citysparkstorage.blob.core.windows.net/portalimages/portalimages/4f8e0bc0-d96a-45df-9df8-751802b8a595.small.png</d2p1:SmallImg><d2p1:Sponsor i:nil="true" /><d2p1:SubmitPID>391001</d2p1:SubmitPID><d2p1:Tags xmlns:d4p1="http://schemas.microsoft.com/2003/10/Serialization/Arrays"><d4p1:int>167</d4p1:int><d4p1:int>10048</d4p1:int><d4p1:int>38</d4p1:int><d4p1:int>6</d4p1:int></d2p1:Tags><d2p1:Tickets><d2p1:jsLink><d2p1:name>The Dam Train Race</d2p1:name><d2p1:revP>0</d2p1:revP><d2p1:url>http://thedamtrainrace.com/</d2p1:url></d2p1:jsLink></d2p1:Tickets><d2p1:Venue>Heber Valley Historic Railroad</d2p1:Venue><d2p1:Zip>84049</d2p1:Zip><d2p1:ct><d2p1:email>support@thedamtrainrace.com</d2p1:email><d2p1:name i:nil="true" /><d2p1:org i:nil="true" /><d2p1:phone i:nil="true" /></d2p1:ct><d2p1:enhance>false</d2p1:enhance><d2p1:latitude>40.4874382019043</d2p1:latitude><d2p1:lm>2016-09-09T20:24:27.133Z</d2p1:lm><d2p1:longitude>-111.48143005371094</d2p1:longitude></d2p1:jsEvent><d2p1:jsEvent><d2p1:Address>300 W. 300 South</d2p1:Address><d2p1:AllDay>false</d2p1:AllDay><d2p1:BiasTags xmlns:d4p1="http://schemas.microsoft.com/2003/10/Serialization/Arrays" i:nil="true" /><d2p1:CityState>Salt Lake City, UT</d2p1:CityState><d2p1:Date>2016-10-01T00:00:00Z</d2p1:Date><d2p1:DateEnd>2016-10-01T14:00:00Z</d2p1:DateEnd><d2p1:DateStart>2016-10-01T08:00:00Z</d2p1:DateStart><d2p1:Description>From its inception in 1992, the Downtown Farmers Market has become a summer tradition for Salt Lake City residents and visitors. Located in historic Pioneer Park, the Saturday Farmers Market has infused vitality into the middle ground between East Bench and West Side neighborhoods.</d2p1:Description><d2p1:Distance>0.6</d2p1:Distance><d2p1:Free>true</d2p1:Free><d2p1:HasTime>true</d2p1:HasTime><d2p1:Id>ca8b578d6a7f4ab099b23a0c64966596</d2p1:Id><d2p1:Images><d2p1:jsImg><d2p1:id>1</d2p1:id><d2p1:url>https://citysparkstorage.blob.core.windows.net/portalimages/portalimages/7a5fa526-ae1c-4de0-925d-879520be27e9.large.png</d2p1:url></d2p1:jsImg></d2p1:Images><d2p1:IsPromotion>false</d2p1:IsPromotion><d2p1:Labels xmlns:d4p1="http://schemas.microsoft.com/2003/10/Serialization/Arrays"><d4p1:string>FarmersMarket</d4p1:string></d2p1:Labels><d2p1:Links><d2p1:jsLink><d2p1:name>Downtown Farmers Market</d2p1:name><d2p1:revP>0</d2p1:revP><d2p1:url>http://www.slcfarmersmarket.org/markets/saturday-farmers-market</d2p1:url></d2p1:jsLink></d2p1:Links><d2p1:Media i:nil="true" /><d2p1:MediumImg>https://citysparkstorage.blob.core.windows.net/portalimages/portalimages/7a5fa526-ae1c-4de0-925d-879520be27e9.medium.png</d2p1:MediumImg><d2p1:Name>Downtown Farmers Market</d2p1:Name><d2p1:Occurances i:nil="true" /><d2p1:PId>2178423</d2p1:PId><d2p1:Picked>false</d2p1:Picked><d2p1:PopularityIndex>14</d2p1:PopularityIndex><d2p1:Price i:nil="true" /><d2p1:PriceHigh i:nil="true" /><d2p1:PriceText i:nil="true" /><d2p1:SmallImg>https://citysparkstorage.blob.core.windows.net/portalimages/portalimages/7a5fa526-ae1c-4de0-925d-879520be27e9.small.png</d2p1:SmallImg><d2p1:Sponsor i:nil="true" /><d2p1:SubmitPID>317473</d2p1:SubmitPID><d2p1:Tags xmlns:d4p1="http://schemas.microsoft.com/2003/10/Serialization/Arrays"><d4p1:int>76</d4p1:int><d4p1:int>385</d4p1:int><d4p1:int>54</d4p1:int></d2p1:Tags><d2p1:Tickets /><d2p1:Venue>Pioneer Park</d2p1:Venue><d2p1:Zip>84101</d2p1:Zip><d2p1:ct i:nil="true" /><d2p1:enhance>false</d2p1:enhance><d2p1:latitude>40.762642845511436</d2p1:latitude><d2p1:lm>2016-06-08T17:40:45.264Z</d2p1:lm><d2p1:longitude>-111.8997598439455</d2p1:longitude></d2p1:jsEvent><d2p1:jsEvent><d2p1:Address>201 Presidents Cir</d2p1:Address><d2p1:AllDay>false</d2p1:AllDay><d2p1:BiasTags xmlns:d4p1="http://schemas.microsoft.com/2003/10/Serialization/Arrays" i:nil="true" /><d2p1:CityState>Salt Lake City, UT</d2p1:CityState><d2p1:Date>2016-10-01T00:00:00Z</d2p1:Date><d2p1:DateEnd i:nil="true" /><d2p1:DateStart>2016-10-01T09:00:00Z</d2p1:DateStart><d2p1:Description>Registration for creative dance, satellite, ballet, hip hop, and Dancers with Disabilities classes for the the 2016-2017 school year is now available.It should be an amazing year of dance.</d2p1:Description><d2p1:Distance>2</d2p1:Distance><d2p1:Free>false</d2p1:Free><d2p1:HasTime>true</d2p1:HasTime><d2p1:Id>990ed447eee047aba6624879be8758d9</d2p1:Id><d2p1:Images><d2p1:jsImg><d2p1:id>1</d2p1:id><d2p1:url>https://citysparkstorage.blob.core.windows.net/portalimages/portalimages/7ed541cf-791e-4cf0-9729-b4d08c053230.large.png</d2p1:url></d2p1:jsImg></d2p1:Images><d2p1:IsPromotion>false</d2p1:IsPromotion><d2p1:Labels xmlns:d4p1="http://schemas.microsoft.com/2003/10/Serialization/Arrays" /><d2p1:Links /><d2p1:Media i:nil="true" /><d2p1:MediumImg>https://citysparkstorage.blob.core.windows.net/portalimages/portalimages/7ed541cf-791e-4cf0-9729-b4d08c053230.medium.png</d2p1:MediumImg><d2p1:Name>Tanner Dance Classes</d2p1:Name><d2p1:Occurances i:nil="true" /><d2p1:PId>2628342</d2p1:PId><d2p1:Picked>false</d2p1:Picked><d2p1:PopularityIndex>10</d2p1:PopularityIndex><d2p1:Price>100</d2p1:Price><d2p1:PriceHigh>750</d2p1:PriceHigh><d2p1:PriceText i:nil="true" /><d2p1:SmallImg>https://citysparkstorage.blob.core.windows.net/portalimages/portalimages/7ed541cf-791e-4cf0-9729-b4d08c053230.small.png</d2p1:SmallImg><d2p1:Sponsor i:nil="true" /><d2p1:SubmitPID i:nil="true" /><d2p1:Tags xmlns:d4p1="http://schemas.microsoft.com/2003/10/Serialization/Arrays"><d4p1:int>2</d4p1:int><d4p1:int>17</d4p1:int><d4p1:int>18</d4p1:int></d2p1:Tags><d2p1:Tickets><d2p1:jsLink><d2p1:name>Tanner Dance Classes</d2p1:name><d2p1:revP>0</d2p1:revP><d2p1:url>http://www.tannerdance.utah.edu/</d2p1:url></d2p1:jsLink></d2p1:Tickets><d2p1:Venue>The University of Utah</d2p1:Venue><d2p1:Zip>84112</d2p1:Zip><d2p1:ct i:nil="true" /><d2p1:enhance>false</d2p1:enhance><d2p1:latitude>40.7655087858</d2p1:latitude><d2p1:lm>2016-07-31T17:09:19.314Z</d2p1:lm><d2p1:longitude>-111.8498969078</d2p1:longitude></d2p1:jsEvent><d2p1:jsEvent><d2p1:Address>151 S. 1100 W.</d2p1:Address><d2p1:AllDay>false</d2p1:AllDay><d2p1:BiasTags xmlns:d4p1="http://schemas.microsoft.com/2003/10/Serialization/Arrays" i:nil="true" /><d2p1:CityState>Farmington, UT</d2p1:CityState><d2p1:Date>2016-10-01T00:00:00Z</d2p1:Date><d2p1:DateEnd>2016-10-01T14:00:00Z</d2p1:DateEnd><d2p1:DateStart>2016-10-01T09:00:00Z</d2p1:DateStart><d2p1:Description>DogFest Walk 'N Roll **Grab a Leash! **Join the fun at this accessible, family- and dog-friendly walk and festival, benefiting Canine Companions for Independence and the mission of providing highly trained assistance dogs to people with disabilities free of charge.

Register for free

Form a team

Collect donations

Walk 'n roll

Change a life</d2p1:Description><d2p1:Distance>15.2</d2p1:Distance><d2p1:Free>true</d2p1:Free><d2p1:HasTime>true</d2p1:HasTime><d2p1:Id>4a6fe0b93c564b1489b966e2c516cd48</d2p1:Id><d2p1:Images><d2p1:jsImg><d2p1:id>1</d2p1:id><d2p1:url>https://citysparkstorage.blob.core.windows.net/portalimages/portalimages/a51111ad-4b06-4c54-8877-c442aa46f74c.large.png</d2p1:url></d2p1:jsImg></d2p1:Images><d2p1:IsPromotion>false</d2p1:IsPromotion><d2p1:Labels xmlns:d4p1="http://schemas.microsoft.com/2003/10/Serialization/Arrays"><d4p1:string>FestivalFair</d4p1:string></d2p1:Labels><d2p1:Links><d2p1:jsLink><d2p1:name>DogFest Walk 'N Roll</d2p1:name><d2p1:revP>0</d2p1:revP><d2p1:url>http://cci.org/DogFestWasatch</d2p1:url></d2p1:jsLink></d2p1:Links><d2p1:Media i:nil="true" /><d2p1:MediumImg>https://citysparkstorage.blob.core.windows.net/portalimages/portalimages/a51111ad-4b06-4c54-8877-c442aa46f74c.medium.png</d2p1:MediumImg><d2p1:Name>DogFest Walk 'N Roll</d2p1:Name><d2p1:Occurances i:nil="true" /><d2p1:PId>2709068</d2p1:PId><d2p1:Picked>false</d2p1:Picked><d2p1:PopularityIndex>38</d2p1:PopularityIndex><d2p1:Price i:nil="true" /><d2p1:PriceHigh i:nil="true" /><d2p1:PriceText i:nil="true" /><d2p1:SmallImg>https://citysparkstorage.blob.core.windows.net/portalimages/portalimages/a51111ad-4b06-4c54-8877-c442aa46f74c.small.png</d2p1:SmallImg><d2p1:Sponsor i:nil="true" /><d2p1:SubmitPID>374344</d2p1:SubmitPID><d2p1:Tags xmlns:d4p1="http://schemas.microsoft.com/2003/10/Serialization/Arrays"><d4p1:int>69</d4p1:int><d4p1:int>67</d4p1:int><d4p1:int>31</d4p1:int><d4p1:int>5</d4p1:int><d4p1:int>10</d4p1:int><d4p1:int>11</d4p1:int></d2p1:Tags><d2p1:Tickets><d2p1:jsLink><d2p1:name>DogFest Walk 'N Roll</d2p1:name><d2p1:revP>0</d2p1:revP><d2p1:url>http://cci.org/DogFestWasatch</d2p1:url></d2p1:jsLink></d2p1:Tickets><d2p1:Venue>Legacy Events Center</d2p1:Venue><d2p1:Zip>84025</d2p1:Zip><d2p1:ct><d2p1:email>chpalmer68@yahoo.com</d2p1:email><d2p1:name>Charlene Palmer, Volunteer</d2p1:name><d2p1:org>Canine Companions for Independence</d2p1:org><d2p1:phone>801-597-4419</d2p1:phone></d2p1:ct><d2p1:enhance>false</d2p1:enhance><d2p1:latitude>40.979645624756813</d2p1:latitude><d2p1:lm>2016-08-22T14:57:54.562Z</d2p1:lm><d2p1:longitude>-111.91128596663475</d2p1:longitude></d2p1:jsEvent><d2p1:jsEvent><d2p1:Address>401 East 200 South</d2p1:Address><d2p1:AllDay>false</d2p1:AllDay><d2p1:BiasTags xmlns:d4p1="http://schemas.microsoft.com/2003/10/Serialization/Arrays" i:nil="true" /><d2p1:CityState>Salt Lake City, UT</d2p1:CityState><d2p1:Date>2016-10-01T00:00:00Z</d2p1:Date><d2p1:DateEnd i:nil="true" /><d2p1:DateStart>2016-10-01T09:00:00Z</d2p1:DateStart><d2p1:Description>The First Annual Zion Art Exhibition is an opportunity to view the winning works of our first competition, showcasing LDS artists in conjunction General Conference in downtown SLC. Come and meet the artists, learn about their works, and help us spread the word of the amazing talents of the more than 10,000 LDS artists working today.</d2p1:Description><d2p1:Distance>0.2</d2p1:Distance><d2p1:Free>true</d2p1:Free><d2p1:HasTime>true</d2p1:HasTime><d2p1:Id>d4dec1be1e9c498ba0838a1cf562339b</d2p1:Id><d2p1:Images><d2p1:jsImg><d2p1:id>1</d2p1:id><d2p1:url>https://citysparkstorage.blob.core.windows.net/portalimages/portalimages/babbc3bd-594b-4bc9-b868-5bf7cf0388ce.large.png</d2p1:url></d2p1:jsImg></d2p1:Images><d2p1:IsPromotion>false</d2p1:IsPromotion><d2p1:Labels xmlns:d4p1="http://schemas.microsoft.com/2003/10/Serialization/Arrays"><d4p1:string>ArtExhibit</d4p1:string></d2p1:Labels><d2p1:Links><d2p1:jsLink><d2p1:name>Zion Art Exhibition</d2p1:name><d2p1:revP>0</d2p1:revP><d2p1:url>http://zionartsociety.org</d2p1:url></d2p1:jsLink></d2p1:Links><d2p1:Media i:nil="true" /><d2p1:MediumImg>https://citysparkstorage.blob.core.windows.net/portalimages/portalimages/babbc3bd-594b-4bc9-b868-5bf7cf0388ce.medium.png</d2p1:MediumImg><d2p1:Name>Zion Art Exhibition</d2p1:Name><d2p1:Occurances i:nil="true" /><d2p1:PId>2762927</d2p1:PId><d2p1:Picked>false</d2p1:Picked><d2p1:PopularityIndex>8</d2p1:PopularityIndex><d2p1:Price i:nil="true" /><d2p1:PriceHigh i:nil="true" /><d2p1:PriceText i:nil="true" /><d2p1:SmallImg>https://citysparkstorage.blob.core.windows.net/portalimages/portalimages/babbc3bd-594b-4bc9-b868-5bf7cf0388ce.small.png</d2p1:SmallImg><d2p1:Sponsor i:nil="true" /><d2p1:SubmitPID>389641</d2p1:SubmitPID><d2p1:Tags xmlns:d4p1="http://schemas.microsoft.com/2003/10/Serialization/Arrays"><d4p1:int>10159</d4p1:int><d4p1:int>23</d4p1:int><d4p1:int>3</d4p1:int><d4p1:int>22</d4p1:int></d2p1:Tags><d2p1:Tickets /><d2p1:Venue>Anthony's Fine Art</d2p1:Venue><d2p1:Zip>84101</d2p1:Zip><d2p1:ct><d2p1:email>contact@zionartsociety.org</d2p1:email><d2p1:name>Eric Biggart</d2p1:name><d2p1:org>Zion Art Society</d2p1:org><d2p1:phone>801-369-8894</d2p1:phone></d2p1:ct><d2p1:enhance>false</d2p1:enhance><d2p1:latitude>40.760442763566971</d2p1:latitude><d2p1:lm>2016-09-08T14:13:25.467Z</d2p1:lm><d2p1:longitude>-111.88530005514622</d2p1:longitude></d2p1:jsEvent><d2p1:jsEvent><d2p1:Address>320 E 3900 S</d2p1:Address><d2p1:AllDay>false</d2p1:AllDay><d2p1:BiasTags xmlns:d4p1="http://schemas.microsoft.com/2003/10/Serialization/Arrays" i:nil="true" /><d2p1:CityState>Salt Lake City, UT</d2p1:CityState><d2p1:Date>2016-10-01T00:00:00Z</d2p1:Date><d2p1:DateEnd i:nil="true" /><d2p1:DateStart>2016-10-01T09:00:00Z</d2p1:DateStart><d2p1:Description>This is a charity ride event\.  We are launching a 501c\(3\) non\-profit foundation called The Riderz Foundation\.  We assist injured motorcyclists who are in distress by helping them with education, recovery and support\.  When a rider goes down, the Riderz step up\.  
The event will have a concert with live music, food trucks, raffles, games, auctions, prize drawings, poker run, best bike in show and best pin\-up girl contests\.</d2p1:Description><d2p1:Distance>5.1</d2p1:Distance><d2p1:Free>false</d2p1:Free><d2p1:HasTime>true</d2p1:HasTime><d2p1:Id>e2af9dc8c3f7402d9089a722dd5e052d</d2p1:Id><d2p1:Images><d2p1:jsImg><d2p1:id>1</d2p1:id><d2p1:url>https://citysparkstorage.blob.core.windows.net/portalimages/portalimages/ac995d11-1a1a-4f81-a968-ce996e1f275d.large.png</d2p1:url></d2p1:jsImg></d2p1:Images><d2p1:IsPromotion>false</d2p1:IsPromotion><d2p1:Labels xmlns:d4p1="http://schemas.microsoft.com/2003/10/Serialization/Arrays" /><d2p1:Links /><d2p1:Media i:nil="true" /><d2p1:MediumImg>https://citysparkstorage.blob.core.windows.net/portalimages/portalimages/ac995d11-1a1a-4f81-a968-ce996e1f275d.medium.png</d2p1:MediumImg><d2p1:Name>The Riderz Foundation Rockabilly Charity Ride Event &amp; Concert</d2p1:Name><d2p1:Occurances i:nil="true" /><d2p1:PId>2774494</d2p1:PId><d2p1:Picked>false</d2p1:Picked><d2p1:PopularityIndex>15</d2p1:PopularityIndex><d2p1:Price>10</d2p1:Price><d2p1:PriceHigh>35</d2p1:PriceHigh><d2p1:PriceText i:nil="true" /><d2p1:SmallImg>https://citysparkstorage.blob.core.windows.net/portalimages/portalimages/ac995d11-1a1a-4f81-a968-ce996e1f275d.small.png</d2p1:SmallImg><d2p1:Sponsor i:nil="true" /><d2p1:SubmitPID i:nil="true" /><d2p1:Tags xmlns:d4p1="http://schemas.microsoft.com/2003/10/Serialization/Arrays"><d4p1:int>2</d4p1:int><d4p1:int>10262</d4p1:int><d4p1:int>17</d4p1:int><d4p1:int>239</d4p1:int><d4p1:int>86</d4p1:int><d4p1:int>6</d4p1:int><d4p1:int>144</d4p1:int><d4p1:int>196</d4p1:int><d4p1:int>37</d4p1:int></d2p1:Tags><d2p1:Tickets><d2p1:jsLink><d2p1:name>The Riderz Foundation Rockabilly Charity Ride Event &amp; Concert</d2p1:name><d2p1:revP>0</d2p1:revP><d2p1:url>http://www.theriderzfoundation.org</d2p1:url></d2p1:jsLink></d2p1:Tickets><d2p1:Venue>The American Legion</d2p1:Venue><d2p1:Zip>84101</d2p1:Zip><d2p1:ct i:nil="true" /><d2p1:enhance>false</d2p1:enhance><d2p1:latitude>40.686454772949219</d2p1:latitude><d2p1:lm>2016-09-11T00:31:55.228Z</d2p1:lm><d2p1:longitude>-111.88188934326172</d2p1:longitude></d2p1:jsEvent><d2p1:jsEvent><d2p1:Address>325 Hwy. 138</d2p1:Address><d2p1:AllDay>false</d2p1:AllDay><d2p1:BiasTags xmlns:d4p1="http://schemas.microsoft.com/2003/10/Serialization/Arrays" i:nil="true" /><d2p1:CityState>Stansbury Park, UT</d2p1:CityState><d2p1:Date>2016-10-01T00:00:00Z</d2p1:Date><d2p1:DateEnd i:nil="true" /><d2p1:DateStart>2016-10-01T09:00:00Z</d2p1:DateStart><d2p1:Description>Come visit our Harvest Days/Farmers Market where local farmers come to sell their produce and we also have other vendors as well. Come early for the best selection. While you're here, you can also tour the Benson Grist Mill Historic Site. Hope to see you there!</d2p1:Description><d2p1:Distance>23</d2p1:Distance><d2p1:Free>true</d2p1:Free><d2p1:HasTime>true</d2p1:HasTime><d2p1:Id>84c023b23ec34c7bb86f41db8b784a91</d2p1:Id><d2p1:Images><d2p1:jsImg><d2p1:id>1</d2p1:id><d2p1:url>https://citysparkstorage.blob.core.windows.net/portalimages/portalimages/b52e9d77-dd16-4ac8-9e9e-8ba8856cef3c.large.png</d2p1:url></d2p1:jsImg></d2p1:Images><d2p1:IsPromotion>false</d2p1:IsPromotion><d2p1:Labels xmlns:d4p1="http://schemas.microsoft.com/2003/10/Serialization/Arrays" /><d2p1:Links><d2p1:jsLink><d2p1:name>Harvest Days/Farmers Market</d2p1:name><d2p1:revP>0</d2p1:revP><d2p1:url>http://www.bensonmill.org</d2p1:url></d2p1:jsLink></d2p1:Links><d2p1:Media i:nil="true" /><d2p1:MediumImg>https://citysparkstorage.blob.core.windows.net/portalimages/portalimages/b52e9d77-dd16-4ac8-9e9e-8ba8856cef3c.medium.png</d2p1:MediumImg><d2p1:Name>Harvest Days/Farmers Market</d2p1:Name><d2p1:Occurances i:nil="true" /><d2p1:PId>2492077</d2p1:PId><d2p1:Picked>false</d2p1:Picked><d2p1:PopularityIndex>19</d2p1:PopularityIndex><d2p1:Price>0</d2p1:Price><d2p1:PriceHigh>0</d2p1:PriceHigh><d2p1:PriceText i:nil="true" /><d2p1:SmallImg>https://citysparkstorage.blob.core.windows.net/portalimages/portalimages/b52e9d77-dd16-4ac8-9e9e-8ba8856cef3c.small.png</d2p1:SmallImg><d2p1:Sponsor i:nil="true" /><d2p1:SubmitPID i:nil="true" /><d2p1:Tags xmlns:d4p1="http://schemas.microsoft.com/2003/10/Serialization/Arrays"><d4p1:int>76</d4p1:int><d4p1:int>385</d4p1:int><d4p1:int>54</d4p1:int><d4p1:int>51</d4p1:int><d4p1:int>15</d4p1:int><d4p1:int>79</d4p1:int></d2p1:Tags><d2p1:Tickets /><d2p1:Venue>Benson Grist Mill</d2p1:Venue><d2p1:Zip i:nil="true" /><d2p1:ct i:nil="true" /><d2p1:enhance>false</d2p1:enhance><d2p1:latitude>40.647851005196571</d2p1:latitude><d2p1:lm>2016-09-19T23:11:36.46Z</d2p1:lm><d2p1:longitude>-112.30136699974537</d2p1:longitude></d2p1:jsEvent><d2p1:jsEvent><d2p1:Address>160 E 200 S, #B</d2p1:Address><d2p1:AllDay>false</d2p1:AllDay><d2p1:BiasTags xmlns:d4p1="http://schemas.microsoft.com/2003/10/Serialization/Arrays" i:nil="true" /><d2p1:CityState>Salt Lake City, UT</d2p1:CityState><d2p1:Date>2016-10-01T00:00:00Z</d2p1:Date><d2p1:DateEnd>2016-10-01T13:00:00Z</d2p1:DateEnd><d2p1:DateStart>2016-10-01T09:30:00Z</d2p1:DateStart><d2p1:Description>Learn the distinctive style and techniques of screen printing, the art form made famous by Andy Warhol. Demonstrations and hands-on experience will guide you through each step, from creating an image to preparing the screen to printing: first a simple image to paper, then a two-color image to paper and finally a one-color image to a wearable t-shirt. Learn to use screen printing equipment and materials safely and effectively. Special fee includes screen printing screen and a tee-shirt to take home at the end of class. Class is limited to eight people. No artistic experience is necessary.</d2p1:Description><d2p1:Distance>0.4</d2p1:Distance><d2p1:Free>false</d2p1:Free><d2p1:HasTime>true</d2p1:HasTime><d2p1:Id>739aef7ef74d40f7a1d0489d7e9268e8</d2p1:Id><d2p1:Images><d2p1:jsImg><d2p1:id>1</d2p1:id><d2p1:url>https://citysparkstorage.blob.core.windows.net/portalimages/portalimages/601e8de3-e3f3-4957-aa5e-aa8877132425.large.png</d2p1:url></d2p1:jsImg></d2p1:Images><d2p1:IsPromotion>false</d2p1:IsPromotion><d2p1:Labels xmlns:d4p1="http://schemas.microsoft.com/2003/10/Serialization/Arrays" /><d2p1:Links><d2p1:jsLink><d2p1:name>Screen Printing (LLCFT 224)</d2p1:name><d2p1:revP>0</d2p1:revP><d2p1:url>https://continue.utah.edu/lifelong/class/llcft_224_screen_printing#sthash.cVGeEkRx.dpuf</d2p1:url></d2p1:jsLink></d2p1:Links><d2p1:Media i:nil="true" /><d2p1:MediumImg>https://citysparkstorage.blob.core.windows.net/portalimages/portalimages/601e8de3-e3f3-4957-aa5e-aa8877132425.medium.png</d2p1:MediumImg><d2p1:Name>Screen Printing (LLCFT 224)</d2p1:Name><d2p1:Occurances i:nil="true" /><d2p1:PId>2666644</d2p1:PId><d2p1:Picked>false</d2p1:Picked><d2p1:PopularityIndex>7</d2p1:PopularityIndex><d2p1:Price>214.00</d2p1:Price><d2p1:PriceHigh>214.00</d2p1:PriceHigh><d2p1:PriceText>Tuition: $179.00 + Special Fee: $35.00 = $214.00</d2p1:PriceText><d2p1:SmallImg>https://citysparkstorage.blob.core.windows.net/portalimages/portalimages/601e8de3-e3f3-4957-aa5e-aa8877132425.small.png</d2p1:SmallImg><d2p1:Sponsor i:nil="true" /><d2p1:SubmitPID>363330</d2p1:SubmitPID><d2p1:Tags xmlns:d4p1="http://schemas.microsoft.com/2003/10/Serialization/Arrays"><d4p1:int>41</d4p1:int><d4p1:int>7</d4p1:int></d2p1:Tags><d2p1:Tickets><d2p1:jsLink><d2p1:name>Screen Printing (LLCFT 224)</d2p1:name><d2p1:revP>0</d2p1:revP><d2p1:url>https://continue.utah.edu/lifelong/class/llcft_224_screen_printing#sthash.cVGeEkRx.dpuf</d2p1:url></d2p1:jsLink></d2p1:Tickets><d2p1:Venue>Copper Palate Press</d2p1:Venue><d2p1:Zip>84101</d2p1:Zip><d2p1:ct><d2p1:email>jonathan.harman@utah.edu</d2p1:email><d2p1:name>Jonathan Harman</d2p1:name><d2p1:org>University of Utah Continuing Education and Community Engagement / Lifelong Learning</d2p1:org><d2p1:phone>801-585-5184</d2p1:phone></d2p1:ct><d2p1:enhance>false</d2p1:enhance><d2p1:latitude>40.765888318419456</d2p1:latitude><d2p1:lm>2016-08-09T16:50:49.254Z</d2p1:lm><d2p1:longitude>-111.88541941344738</d2p1:longitude></d2p1:jsEvent><d2p1:jsEvent><d2p1:Address>3601 S. 2700 W.</d2p1:Address><d2p1:AllDay>false</d2p1:AllDay><d2p1:BiasTags xmlns:d4p1="http://schemas.microsoft.com/2003/10/Serialization/Arrays" i:nil="true" /><d2p1:CityState>West Valley City, UT</d2p1:CityState><d2p1:Date>2016-10-01T00:00:00Z</d2p1:Date><d2p1:DateEnd i:nil="true" /><d2p1:DateStart>2016-10-01T10:00:00Z</d2p1:DateStart><d2p1:Description>The Junior League is excited to host our
7th Annual Touch\-A\-Truck event\!
Touch\-A\-Truck is a family fun event offering kids of all ages a hands on experience to explore large vehicles, see how they work, and even sit in the drivers seat\!  These large vehicles include construction trucks, utility trucks, emergency responder vehicles, helicopters, and more\!
Quiet hour will be held from 10a\-11a for kids who might be scared of horns and sirens\.
 Go to www\.jlslc\.org to purchase tickets\! 
Individual Tickets $5
Family Pass \(up to 5 individuals\) $20
If you are interested in partnering with us for the
2016 Annual Touch a Truck event,
please contact events@jlslc\.org</d2p1:Description><d2p1:Distance>5.8</d2p1:Distance><d2p1:Free>false</d2p1:Free><d2p1:HasTime>true</d2p1:HasTime><d2p1:Id>7549cfe1cf3a4f079d341deee35b91e3</d2p1:Id><d2p1:Images><d2p1:jsImg><d2p1:id>1</d2p1:id><d2p1:url>https://citysparkstorage.blob.core.windows.net/portalimages/portalimages/463f83ea-c4ae-418a-9688-44addf84d15c.large.png</d2p1:url></d2p1:jsImg></d2p1:Images><d2p1:IsPromotion>false</d2p1:IsPromotion><d2p1:Labels xmlns:d4p1="http://schemas.microsoft.com/2003/10/Serialization/Arrays" /><d2p1:Links><d2p1:jsLink><d2p1:name>SUIndependent</d2p1:name><d2p1:revP>0</d2p1:revP><d2p1:url>http://www.jlslc.org</d2p1:url></d2p1:jsLink></d2p1:Links><d2p1:Media i:nil="true" /><d2p1:MediumImg>https://citysparkstorage.blob.core.windows.net/portalimages/portalimages/463f83ea-c4ae-418a-9688-44addf84d15c.medium.png</d2p1:MediumImg><d2p1:Name>7th Annual Touch-A-Truck event!</d2p1:Name><d2p1:Occurances i:nil="true" /><d2p1:PId>2808378</d2p1:PId><d2p1:Picked>false</d2p1:Picked><d2p1:PopularityIndex>28</d2p1:PopularityIndex><d2p1:Price>5</d2p1:Price><d2p1:PriceHigh>20</d2p1:PriceHigh><d2p1:PriceText i:nil="true" /><d2p1:SmallImg>https://citysparkstorage.blob.core.windows.net/portalimages/portalimages/463f83ea-c4ae-418a-9688-44addf84d15c.small.png</d2p1:SmallImg><d2p1:Sponsor i:nil="true" /><d2p1:SubmitPID i:nil="true" /><d2p1:Tags xmlns:d4p1="http://schemas.microsoft.com/2003/10/Serialization/Arrays"><d4p1:int>15</d4p1:int><d4p1:int>79</d4p1:int></d2p1:Tags><d2p1:Tickets><d2p1:jsLink><d2p1:name>SUIndependent</d2p1:name><d2p1:revP>0</d2p1:revP><d2p1:url>http://Individual Tickets $5 Family Pass (up to 5 individuals) $20</d2p1:url></d2p1:jsLink></d2p1:Tickets><d2p1:Venue>Valley Fair Mall</d2p1:Venue><d2p1:Zip>84120</d2p1:Zip><d2p1:ct i:nil="true" /><d2p1:enhance>false</d2p1:enhance><d2p1:latitude>40.694130510091782</d2p1:latitude><d2p1:lm>2016-09-21T18:21:01.758Z</d2p1:lm><d2p1:longitude>-111.95782698690891</d2p1:longitude></d2p1:jsEvent><d2p1:jsEvent><d2p1:Address>1000 S. 900 West</d2p1:Address><d2p1:AllDay>false</d2p1:AllDay><d2p1:BiasTags xmlns:d4p1="http://schemas.microsoft.com/2003/10/Serialization/Arrays" i:nil="true" /><d2p1:CityState>Salt Lake City, UT</d2p1:CityState><d2p1:Date>2016-10-01T00:00:00Z</d2p1:Date><d2p1:DateEnd>2016-10-01T14:00:00Z</d2p1:DateEnd><d2p1:DateStart>2016-10-01T10:00:00Z</d2p1:DateStart><d2p1:Description>The atmosphere at the People's Market is friendly and inviting. Visit with our local artisans, enjoy fresh prepared food, purchase some of the best produce to be found locally, and enjoy the live performances by local musicians.

We have different Special Events through out the Season, including Book Day where you can swap books with others at the Market, and Pet Day when we promote the many rescue organizations who bring out wonderful animals who are in need of good homes. We also promote the talented youth of the community to come: to learn arts and crafts, sell items that they have made themselves, or even perform musically during open mic sessions at the Market.</d2p1:Description><d2p1:Distance>1.7</d2p1:Distance><d2p1:Free>true</d2p1:Free><d2p1:HasTime>true</d2p1:HasTime><d2p1:Id>e01be22273e446e5a9eb11fb8ab56a53</d2p1:Id><d2p1:Images><d2p1:jsImg><d2p1:id>1</d2p1:id><d2p1:url>https://citysparkstorage.blob.core.windows.net/portalimages/portalimages/6ea01022-34cb-402b-92c8-74d72ec1e272.large.png</d2p1:url></d2p1:jsImg></d2p1:Images><d2p1:IsPromotion>false</d2p1:IsPromotion><d2p1:Labels xmlns:d4p1="http://schemas.microsoft.com/2003/10/Serialization/Arrays"><d4p1:string>FarmersMarket</d4p1:string></d2p1:Labels><d2p1:Links><d2p1:jsLink><d2p1:name>9th West Farmers Market</d2p1:name><d2p1:revP>0</d2p1:revP><d2p1:url>http://9thwestfarmersmarket.org</d2p1:url></d2p1:jsLink></d2p1:Links><d2p1:Media i:nil="true" /><d2p1:MediumImg>https://citysparkstorage.blob.core.windows.net/portalimages/portalimages/6ea01022-34cb-402b-92c8-74d72ec1e272.medium.png</d2p1:MediumImg><d2p1:Name>9th West Farmers Market</d2p1:Name><d2p1:Occurances i:nil="true" /><d2p1:PId>2845797</d2p1:PId><d2p1:Picked>false</d2p1:Picked><d2p1:PopularityIndex>11</d2p1:PopularityIndex><d2p1:Price i:nil="true" /><d2p1:PriceHigh i:nil="true" /><d2p1:PriceText i:nil="true" /><d2p1:SmallImg>https://citysparkstorage.blob.core.windows.net/portalimages/portalimages/6ea01022-34cb-402b-92c8-74d72ec1e272.small.png</d2p1:SmallImg><d2p1:Sponsor i:nil="true" /><d2p1:SubmitPID>411155</d2p1:SubmitPID><d2p1:Tags xmlns:d4p1="http://schemas.microsoft.com/2003/10/Serialization/Arrays"><d4p1:int>385</d4p1:int><d4p1:int>74</d4p1:int><d4p1:int>42</d4p1:int><d4p1:int>8</d4p1:int><d4p1:int>12</d4p1:int><d4p1:int>54</d4p1:int><d4p1:int>76</d4p1:int></d2p1:Tags><d2p1:Tickets /><d2p1:Venue>The People's Market</d2p1:Venue><d2p1:Zip>84101</d2p1:Zip><d2p1:ct i:nil="true" /><d2p1:enhance>false</d2p1:enhance><d2p1:latitude>40.748195648193359</d2p1:latitude><d2p1:lm>2016-09-30T17:33:17.7Z</d2p1:lm><d2p1:longitude>-111.91752624511719</d2p1:longitude></d2p1:jsEvent><d2p1:jsEvent><d2p1:Address>125 E 3300 S</d2p1:Address><d2p1:AllDay>false</d2p1:AllDay><d2p1:BiasTags xmlns:d4p1="http://schemas.microsoft.com/2003/10/Serialization/Arrays" i:nil="true" /><d2p1:CityState>Salt Lake City, UT</d2p1:CityState><d2p1:Date>2016-10-01T00:00:00Z</d2p1:Date><d2p1:DateEnd>2016-10-01T12:00:00Z</d2p1:DateEnd><d2p1:DateStart>2016-10-01T10:30:00Z</d2p1:DateStart><d2p1:Description>Calling all gamers! What if there was an event or league for kids that loved competitive games, just like there are for kids that love sports? There is! Enter Minecraft Adventure by Super League Gaming.

___

Kids 6-16 years old are invited to experience a thrilling 90 minutes of fun and friendly competition while playing Minecraft in a movie theatre near you. Dive into a smorgasbord of some of the best games and maps, make friends and enjoy the action on the big screen.

___

Each player has their own laptop, which enables a first-person Point of View of the game. The movie screen offers a Bird's Eye View, showing the action of everyone playing in the theatre. Please check the below link to see visuals highlighting the vibrant, fun-filled gaming action to be had with Minecraft Adventure: https://www.youtube.com/watch?v=tlL1CSNyx6k

___

90 minutes isn’t enough? Sign up for the weekly league events at your local theatre and join a competitive team come October for Metropolis Madness.

___
Note: You must bring a LAPTOP (not tablet or phone) with Minecraft version 1.10 installed.</d2p1:Description><d2p1:Distance>4.1</d2p1:Distance><d2p1:Free>false</d2p1:Free><d2p1:HasTime>true</d2p1:HasTime><d2p1:Id>15778b741c774a53858d0c8a5e809ea3</d2p1:Id><d2p1:Images><d2p1:jsImg><d2p1:id>1</d2p1:id><d2p1:url>https://citysparkstorage.blob.core.windows.net/portalimages/portalimages/f8d02e58-9d97-4418-8237-12dcf28ca50c.large.png</d2p1:url></d2p1:jsImg></d2p1:Images><d2p1:IsPromotion>false</d2p1:IsPromotion><d2p1:Labels xmlns:d4p1="http://schemas.microsoft.com/2003/10/Serialization/Arrays" /><d2p1:Links /><d2p1:Media i:nil="true" /><d2p1:MediumImg>https://citysparkstorage.blob.core.windows.net/portalimages/portalimages/f8d02e58-9d97-4418-8237-12dcf28ca50c.medium.png</d2p1:MediumImg><d2p1:Name>Minecraft Adventure by Super League Gaming in Salt Lake City</d2p1:Name><d2p1:Occurances i:nil="true" /><d2p1:PId>2801824</d2p1:PId><d2p1:Picked>false</d2p1:Picked><d2p1:PopularityIndex>25</d2p1:PopularityIndex><d2p1:Price i:nil="true" /><d2p1:PriceHigh i:nil="true" /><d2p1:PriceText>$20</d2p1:PriceText><d2p1:SmallImg>https://citysparkstorage.blob.core.windows.net/portalimages/portalimages/f8d02e58-9d97-4418-8237-12dcf28ca50c.small.png</d2p1:SmallImg><d2p1:Sponsor i:nil="true" /><d2p1:SubmitPID>399906</d2p1:SubmitPID><d2p1:Tags xmlns:d4p1="http://schemas.microsoft.com/2003/10/Serialization/Arrays"><d4p1:int>358</d4p1:int><d4p1:int>53</d4p1:int><d4p1:int>79</d4p1:int><d4p1:int>15</d4p1:int><d4p1:int>76</d4p1:int></d2p1:Tags><d2p1:Tickets><d2p1:jsLink><d2p1:name>Minecraft Adventure by Super League Gaming in Salt Lake City</d2p1:name><d2p1:revP>0</d2p1:revP><d2p1:url>https://superleague.com/get-tickets/2215</d2p1:url></d2p1:jsLink></d2p1:Tickets><d2p1:Venue>Century 16</d2p1:Venue><d2p1:Zip>84101</d2p1:Zip><d2p1:ct><d2p1:email>gbrown@triplepointpr.com</d2p1:email><d2p1:name>Gentry Brown</d2p1:name><d2p1:org>Super League Gaming</d2p1:org><d2p1:phone>4159558500</d2p1:phone></d2p1:ct><d2p1:enhance>false</d2p1:enhance><d2p1:latitude>40.700340270996094</d2p1:latitude><d2p1:lm>2016-09-20T02:31:39.718Z</d2p1:lm><d2p1:longitude>-111.88698577880859</d2p1:longitude></d2p1:jsEvent><d2p1:jsEvent><d2p1:Address i:nil="true" /><d2p1:AllDay>false</d2p1:AllDay><d2p1:BiasTags xmlns:d4p1="http://schemas.microsoft.com/2003/10/Serialization/Arrays" i:nil="true" /><d2p1:CityState>Salt Lake City, UT</d2p1:CityState><d2p1:Date>2016-10-01T00:00:00Z</d2p1:Date><d2p1:DateEnd i:nil="true" /><d2p1:DateStart>2016-10-01T11:00:00Z</d2p1:DateStart><d2p1:Description>Join us for our 1st annual Cars for K.S.A Fundraiser Car Show.

___

This event is FREE to the public and is a family event. Have an old car? Bring it on down and help support our school. 

We will have Food Trucks, Music, Vendors, Raffles and some amazing cars. All cars must be registered for the event and cost is a $20.00 donation.

So, please come down and support our School!</d2p1:Description><d2p1:Distance>0</d2p1:Distance><d2p1:Free>true</d2p1:Free><d2p1:HasTime>true</d2p1:HasTime><d2p1:Id>c1faed4e7f644f90a698277e626b2ecf</d2p1:Id><d2p1:Images><d2p1:jsImg><d2p1:id>1</d2p1:id><d2p1:url>https://citysparkstorage.blob.core.windows.net/portalimages/portalimages/b5791ade-1be7-4d23-8b31-1a4a017148f7.large.png</d2p1:url></d2p1:jsImg></d2p1:Images><d2p1:IsPromotion>false</d2p1:IsPromotion><d2p1:Labels xmlns:d4p1="http://schemas.microsoft.com/2003/10/Serialization/Arrays" /><d2p1:Links /><d2p1:Media i:nil="true" /><d2p1:MediumImg>https://citysparkstorage.blob.core.windows.net/portalimages/portalimages/b5791ade-1be7-4d23-8b31-1a4a017148f7.medium.png</d2p1:MediumImg><d2p1:Name>Cars for K.S.A (Kearns Saint Anns) Car show Fundraiser</d2p1:Name><d2p1:Occurances i:nil="true" /><d2p1:PId>2777911</d2p1:PId><d2p1:Picked>false</d2p1:Picked><d2p1:PopularityIndex>18</d2p1:PopularityIndex><d2p1:Price>0</d2p1:Price><d2p1:PriceHigh>0</d2p1:PriceHigh><d2p1:PriceText i:nil="true" /><d2p1:SmallImg>https://citysparkstorage.blob.core.windows.net/portalimages/portalimages/b5791ade-1be7-4d23-8b31-1a4a017148f7.small.png</d2p1:SmallImg><d2p1:Sponsor i:nil="true" /><d2p1:SubmitPID i:nil="true" /><d2p1:Tags xmlns:d4p1="http://schemas.microsoft.com/2003/10/Serialization/Arrays"><d4p1:int>76</d4p1:int><d4p1:int>58</d4p1:int><d4p1:int>10032</d4p1:int><d4p1:int>11</d4p1:int><d4p1:int>69</d4p1:int><d4p1:int>15</d4p1:int><d4p1:int>79</d4p1:int></d2p1:Tags><d2p1:Tickets /><d2p1:Venue>Kearns Saint Anns Catholic School</d2p1:Venue><d2p1:Zip i:nil="true" /><d2p1:ct i:nil="true" /><d2p1:enhance>false</d2p1:enhance><d2p1:latitude>40.760311126708984</d2p1:latitude><d2p1:lm>2016-09-12T22:37:27.352Z</d2p1:lm><d2p1:longitude>-111.88822174072266</d2p1:longitude></d2p1:jsEvent><d2p1:jsEvent><d2p1:Address>425 N. 400 West</d2p1:Address><d2p1:AllDay>false</d2p1:AllDay><d2p1:BiasTags xmlns:d4p1="http://schemas.microsoft.com/2003/10/Serialization/Arrays" i:nil="true" /><d2p1:CityState>Salt Lake City, UT</d2p1:CityState><d2p1:Date>2016-10-01T00:00:00Z</d2p1:Date><d2p1:DateEnd>2016-10-01T22:00:00Z</d2p1:DateEnd><d2p1:DateStart>2016-10-01T11:00:00Z</d2p1:DateStart><d2p1:Description>Join us for a 4th West Oktoberfest celebration with Red Rock Brewing and Mountain West Hard Cider libations!

___

Friday, September 30: 3pm - 10pm

Saturday, October 1: 11am - 10pm

Sunday, October 2: 12pm - 5pm

___

Live Bands! And DJ Justin Godina!

Candy's River House - Friday, 7:00pm to 10:00pm

Tony Holiday and the Velvetones - Saturday, 1:00pm to 4:00pm

Hectic Hobo - Saturday, 7:00pm to 10:00pm

Talia Keys - Sunday, 12:00pm to 2:30pm

Michelle Moonshine - Sunday, 2:30pm to 5:00pm

___

Food Trucks!

Poutine Your Mouth, Tacos Don Rafa, SPUDS, Bumblebee's KBBQ &amp; Grill (Saturday only), Shylo's Mobile Cafe (Saturday and Sunday only)

Games!

**corn hole | giant Jenga | ring toss | beer pong | children's craft table | etc. **

$7 admission per person includes a limited edition mug.

VIP admission also available and includes a food buffet catered by Garage On Beck, limited edition mug, and two drink tickets.</d2p1:Description><d2p1:Distance>1.4</d2p1:Distance><d2p1:Free>false</d2p1:Free><d2p1:HasTime>true</d2p1:HasTime><d2p1:Id>889bc1b87f434ffe85734466117bee67</d2p1:Id><d2p1:Images><d2p1:jsImg><d2p1:id>1</d2p1:id><d2p1:url>https://citysparkstorage.blob.core.windows.net/portalimages/portalimages/f01ef2b6-46bb-4e1c-894c-34b925d29263.large.png</d2p1:url></d2p1:jsImg></d2p1:Images><d2p1:IsPromotion>false</d2p1:IsPromotion><d2p1:Labels xmlns:d4p1="http://schemas.microsoft.com/2003/10/Serialization/Arrays"><d4p1:string>CityWeeklySponsoredEvent</d4p1:string><d4p1:string>FestivalFair</d4p1:string></d2p1:Labels><d2p1:Links><d2p1:jsLink><d2p1:name>4th West Oktoberfest</d2p1:name><d2p1:revP>0</d2p1:revP><d2p1:url>http://www.mountainwestcider.com</d2p1:url></d2p1:jsLink></d2p1:Links><d2p1:Media i:nil="true" /><d2p1:MediumImg>https://citysparkstorage.blob.core.windows.net/portalimages/portalimages/f01ef2b6-46bb-4e1c-894c-34b925d29263.medium.png</d2p1:MediumImg><d2p1:Name>4th West Oktoberfest</d2p1:Name><d2p1:Occurances i:nil="true" /><d2p1:PId>2764387</d2p1:PId><d2p1:Picked>false</d2p1:Picked><d2p1:PopularityIndex>213</d2p1:PopularityIndex><d2p1:Price>7</d2p1:Price><d2p1:PriceHigh>15</d2p1:PriceHigh><d2p1:PriceText>$7 admission includes a free limited edition mug!</d2p1:PriceText><d2p1:SmallImg>https://citysparkstorage.blob.core.windows.net/portalimages/portalimages/f01ef2b6-46bb-4e1c-894c-34b925d29263.small.png</d2p1:SmallImg><d2p1:Sponsor i:nil="true" /><d2p1:SubmitPID>401017</d2p1:SubmitPID><d2p1:Tags xmlns:d4p1="http://schemas.microsoft.com/2003/10/Serialization/Arrays"><d4p1:int>31</d4p1:int><d4p1:int>75</d4p1:int><d4p1:int>5</d4p1:int><d4p1:int>12</d4p1:int></d2p1:Tags><d2p1:Tickets><d2p1:jsLink><d2p1:name>4th West Oktoberfest</d2p1:name><d2p1:revP>0</d2p1:revP><d2p1:url>http://4thwestoktoberfest.eventbrite.com</d2p1:url></d2p1:jsLink></d2p1:Tickets><d2p1:Venue>Mountain West Cider</d2p1:Venue><d2p1:Zip>84101</d2p1:Zip><d2p1:ct><d2p1:email>lansia@mountainwestcider.com</d2p1:email><d2p1:name i:nil="true" /><d2p1:org>Mountain West Hard Cider</d2p1:org><d2p1:phone>801-935-4147</d2p1:phone></d2p1:ct><d2p1:enhance>true</d2p1:enhance><d2p1:latitude>40.778005197644234</d2p1:latitude><d2p1:lm>2016-09-20T19:42:47.057Z</d2p1:lm><d2p1:longitude>-111.90294161438942</d2p1:longitude></d2p1:jsEvent><d2p1:jsEvent><d2p1:Address>1511 S. 1500 East</d2p1:Address><d2p1:AllDay>false</d2p1:AllDay><d2p1:BiasTags xmlns:d4p1="http://schemas.microsoft.com/2003/10/Serialization/Arrays" i:nil="true" /><d2p1:CityState>Salt Lake City, UT</d2p1:CityState><d2p1:Date>2016-10-01T00:00:00Z</d2p1:Date><d2p1:DateEnd>2016-10-01T12:00:00Z</d2p1:DateEnd><d2p1:DateStart>2016-10-01T11:00:00Z</d2p1:DateStart><d2p1:Description>Join local author and illustrator, Jake Parker, for a reading and signing of his new picture book, Little Bot and Sparrow.
When Little Bot is thrown out with the garbage, he meets his first true friend, a bird named Sparrow, who takes him under her wing. Sparrow teaches Little Bot about the perils of flying, her wild world, and the importance of dreaming.
As winter arrives, Sparrow must leave and fly south, and they share a tearful good bye. Little Bot revisits where he and Sparrow shared happy memories, and that night, for the first time, he dreams--of him and Sparrow taking flight together.
Places in the signing line are reserved for those who purchase a copy of Little Bot and Sparrow from The King's English.
GET YOUR COPY NOW! Pre-order your signed copy of Little Bot and Sparrow today, by either calling the store at 801-484-9100 or ordering online. Please specify if you will be attending the event and if you want your book personalized.</d2p1:Description><d2p1:Distance>2.7</d2p1:Distance><d2p1:Free>true</d2p1:Free><d2p1:HasTime>true</d2p1:HasTime><d2p1:Id>b06553414e3b4e32aee647dac03be3f6</d2p1:Id><d2p1:Images><d2p1:jsImg><d2p1:id>1</d2p1:id><d2p1:url>https://citysparkstorage.blob.core.windows.net/portalimages/portalimages/2e6788e4-f607-40a1-b91f-392b7218eb0f.large.png</d2p1:url></d2p1:jsImg></d2p1:Images><d2p1:IsPromotion>false</d2p1:IsPromotion><d2p1:Labels xmlns:d4p1="http://schemas.microsoft.com/2003/10/Serialization/Arrays"><d4p1:string>Author</d4p1:string></d2p1:Labels><d2p1:Links><d2p1:jsLink><d2p1:name>Jake Parker: Little Bot and Sparrow</d2p1:name><d2p1:revP>0</d2p1:revP><d2p1:url>http://www.facebook.com/events/175866172824359</d2p1:url></d2p1:jsLink></d2p1:Links><d2p1:Media i:nil="true" /><d2p1:MediumImg>https://citysparkstorage.blob.core.windows.net/portalimages/portalimages/ad034b0f-f22a-4d8a-b026-fd5fe0200cb4.medium.png</d2p1:MediumImg><d2p1:Name>Jake Parker: Little Bot and Sparrow</d2p1:Name><d2p1:Occurances i:nil="true" /><d2p1:PId>2713845</d2p1:PId><d2p1:Picked>false</d2p1:Picked><d2p1:PopularityIndex>6</d2p1:PopularityIndex><d2p1:Price i:nil="true" /><d2p1:PriceHigh i:nil="true" /><d2p1:PriceText i:nil="true" /><d2p1:SmallImg>https://citysparkstorage.blob.core.windows.net/portalimages/portalimages/ad034b0f-f22a-4d8a-b026-fd5fe0200cb4.small.png</d2p1:SmallImg><d2p1:Sponsor i:nil="true" /><d2p1:SubmitPID>402203</d2p1:SubmitPID><d2p1:Tags xmlns:d4p1="http://schemas.microsoft.com/2003/10/Serialization/Arrays"><d4p1:int>4</d4p1:int><d4p1:int>189</d4p1:int></d2p1:Tags><d2p1:Tickets /><d2p1:Venue>The King's English Bookshop</d2p1:Venue><d2p1:Zip>84101</d2p1:Zip><d2p1:ct i:nil="true" /><d2p1:enhance>false</d2p1:enhance><d2p1:latitude>40.73681640625</d2p1:latitude><d2p1:lm>2016-09-21T19:48:10.781Z</d2p1:lm><d2p1:longitude>-111.84763336181641</d2p1:longitude></d2p1:jsEvent><d2p1:jsEvent><d2p1:Address>175 E. 200 South</d2p1:Address><d2p1:AllDay>false</d2p1:AllDay><d2p1:BiasTags xmlns:d4p1="http://schemas.microsoft.com/2003/10/Serialization/Arrays" i:nil="true" /><d2p1:CityState>Salt Lake City, UT</d2p1:CityState><d2p1:Date>2016-10-01T00:00:00Z</d2p1:Date><d2p1:DateEnd>2016-10-01T16:00:00Z</d2p1:DateEnd><d2p1:DateStart>2016-10-01T12:00:00Z</d2p1:DateStart><d2p1:Description>CUAC is pleased to present Discover Zaqistan: The Art of Adventure by the Zaqistan Tourism Board. The Republic of Zaqistan is located just west of the Great Salt Lake. Founded in 2005 by New York City-based artist Zaq Landsberg as a response to the political climate at the time, the project continues to be conceptually tied to current events. This year, Zaqistan is opening up its doors to tourism and partnering with *CUAC* to host expeditions into the desolate nation as well as an exhibition on the country.</d2p1:Description><d2p1:Distance>0.4</d2p1:Distance><d2p1:Free>true</d2p1:Free><d2p1:HasTime>true</d2p1:HasTime><d2p1:Id>fc195f910c8a4e39acbfefcd5ef65e70</d2p1:Id><d2p1:Images><d2p1:jsImg><d2p1:id>1</d2p1:id><d2p1:url>https://citysparkstorage.blob.core.windows.net/portalimages/portalimages/b2bb1fa6-ff15-43a3-8402-6bec78b69aa1.large.png</d2p1:url></d2p1:jsImg></d2p1:Images><d2p1:IsPromotion>false</d2p1:IsPromotion><d2p1:Labels xmlns:d4p1="http://schemas.microsoft.com/2003/10/Serialization/Arrays"><d4p1:string>ArtExhibit</d4p1:string></d2p1:Labels><d2p1:Links><d2p1:jsLink><d2p1:name>Discover Zaqistan: The Art of Adventure</d2p1:name><d2p1:revP>0</d2p1:revP><d2p1:url>http://cuartcenter.org</d2p1:url></d2p1:jsLink></d2p1:Links><d2p1:Media i:nil="true" /><d2p1:MediumImg>https://citysparkstorage.blob.core.windows.net/portalimages/portalimages/b2bb1fa6-ff15-43a3-8402-6bec78b69aa1.medium.png</d2p1:MediumImg><d2p1:Name>Discover Zaqistan: The Art of Adventure</d2p1:Name><d2p1:Occurances i:nil="true" /><d2p1:PId>2759785</d2p1:PId><d2p1:Picked>false</d2p1:Picked><d2p1:PopularityIndex>14</d2p1:PopularityIndex><d2p1:Price i:nil="true" /><d2p1:PriceHigh i:nil="true" /><d2p1:PriceText i:nil="true" /><d2p1:SmallImg>https://citysparkstorage.blob.core.windows.net/portalimages/portalimages/b2bb1fa6-ff15-43a3-8402-6bec78b69aa1.small.png</d2p1:SmallImg><d2p1:Sponsor i:nil="true" /><d2p1:SubmitPID>388158</d2p1:SubmitPID><d2p1:Tags xmlns:d4p1="http://schemas.microsoft.com/2003/10/Serialization/Arrays"><d4p1:int>32</d4p1:int><d4p1:int>3</d4p1:int><d4p1:int>5</d4p1:int></d2p1:Tags><d2p1:Tickets /><d2p1:Venue>CUAC</d2p1:Venue><d2p1:Zip>84101</d2p1:Zip><d2p1:ct><d2p1:email>art@cuartcenter.org</d2p1:email><d2p1:name>Nancy Rivera</d2p1:name><d2p1:org>CUAC</d2p1:org><d2p1:phone>385-215-6768</d2p1:phone></d2p1:ct><d2p1:enhance>false</d2p1:enhance><d2p1:latitude>40.7657470703125</d2p1:latitude><d2p1:lm>2016-09-07T16:03:56.227Z</d2p1:lm><d2p1:longitude>-111.88483428955078</d2p1:longitude></d2p1:jsEvent><d2p1:jsEvent><d2p1:Address>9750 S 300 West #150E</d2p1:Address><d2p1:AllDay>false</d2p1:AllDay><d2p1:BiasTags xmlns:d4p1="http://schemas.microsoft.com/2003/10/Serialization/Arrays" i:nil="true" /><d2p1:CityState>Sandy, UT</d2p1:CityState><d2p1:Date>2016-10-01T00:00:00Z</d2p1:Date><d2p1:DateEnd>2016-10-01T21:00:00Z</d2p1:DateEnd><d2p1:DateStart>2016-10-01T12:00:00Z</d2p1:DateStart><d2p1:Description>Purchase your tickets to Utah's largest paranormal festival. Meet local paranormal experts, browse the vendor booths, attend the panels conducted by our special panelist. Come down and meet our special guest in person and get to know them. If you order your ticket online prior to the event the price is just $10 plus small ticket fee.
TICKETS PURCHASED AT THE EVENT DOOR WILL BE $15 SO ORDER ONLINE TODAY!!!
We will also be having a monthly investigation in support of this event. And we will be posting guests and events as we get them set up.</d2p1:Description><d2p1:Distance>12.8</d2p1:Distance><d2p1:Free>false</d2p1:Free><d2p1:HasTime>true</d2p1:HasTime><d2p1:Id>3db71fbe129341e09f5a116a55a8bf33</d2p1:Id><d2p1:Images><d2p1:jsImg><d2p1:id>1</d2p1:id><d2p1:url>https://citysparkstorage.blob.core.windows.net/portalimages/portalimages/2f8e89c6-5af3-4fe9-97f5-f4139fd5f862.large.png</d2p1:url></d2p1:jsImg></d2p1:Images><d2p1:IsPromotion>false</d2p1:IsPromotion><d2p1:Labels xmlns:d4p1="http://schemas.microsoft.com/2003/10/Serialization/Arrays"><d4p1:string>FestivalFair</d4p1:string></d2p1:Labels><d2p1:Links><d2p1:jsLink><d2p1:name>2016 Utah Paranormal Festival</d2p1:name><d2p1:revP>0</d2p1:revP><d2p1:url>http://utahparanormalfest.wix.com/utahparanormalfest</d2p1:url></d2p1:jsLink></d2p1:Links><d2p1:Media i:nil="true" /><d2p1:MediumImg>https://citysparkstorage.blob.core.windows.net/portalimages/portalimages/2f8e89c6-5af3-4fe9-97f5-f4139fd5f862.medium.png</d2p1:MediumImg><d2p1:Name>2016 Utah Paranormal Festival</d2p1:Name><d2p1:Occurances i:nil="true" /><d2p1:PId>2275109</d2p1:PId><d2p1:Picked>false</d2p1:Picked><d2p1:PopularityIndex>38</d2p1:PopularityIndex><d2p1:Price>10</d2p1:Price><d2p1:PriceHigh>15</d2p1:PriceHigh><d2p1:PriceText>Pre-purchase ticket at $10</d2p1:PriceText><d2p1:SmallImg>https://citysparkstorage.blob.core.windows.net/portalimages/portalimages/2f8e89c6-5af3-4fe9-97f5-f4139fd5f862.small.png</d2p1:SmallImg><d2p1:Sponsor i:nil="true" /><d2p1:SubmitPID>372193</d2p1:SubmitPID><d2p1:Tags xmlns:d4p1="http://schemas.microsoft.com/2003/10/Serialization/Arrays"><d4p1:int>10051</d4p1:int><d4p1:int>10213</d4p1:int><d4p1:int>31</d4p1:int><d4p1:int>5</d4p1:int><d4p1:int>10032</d4p1:int><d4p1:int>76</d4p1:int></d2p1:Tags><d2p1:Tickets><d2p1:jsLink><d2p1:name>2016 Utah Paranormal Festival</d2p1:name><d2p1:revP>0</d2p1:revP><d2p1:url>http://www.meetup.com/Paranormal-Events-of-Utah/events/226128897/</d2p1:url></d2p1:jsLink></d2p1:Tickets><d2p1:Venue>Karen Gail Miller Conference Center - KGMC</d2p1:Venue><d2p1:Zip>84094</d2p1:Zip><d2p1:ct><d2p1:email>utahparanormalfestival@outlook.com</d2p1:email><d2p1:name i:nil="true" /><d2p1:org>Badass Spirit Outlaws</d2p1:org><d2p1:phone i:nil="true" /></d2p1:ct><d2p1:enhance>true</d2p1:enhance><d2p1:latitude>40.574806213378906</d2p1:latitude><d2p1:lm>2016-09-19T23:08:20.326Z</d2p1:lm><d2p1:longitude>-111.90279388427734</d2p1:longitude></d2p1:jsEvent><d2p1:jsEvent><d2p1:Address>3925 E. Snowbasin Road</d2p1:Address><d2p1:AllDay>false</d2p1:AllDay><d2p1:BiasTags xmlns:d4p1="http://schemas.microsoft.com/2003/10/Serialization/Arrays" i:nil="true" /><d2p1:CityState>Salt Lake City, UT</d2p1:CityState><d2p1:Date>2016-10-01T00:00:00Z</d2p1:Date><d2p1:DateEnd>2016-10-01T18:00:00Z</d2p1:DateEnd><d2p1:DateStart>2016-10-01T12:00:00Z</d2p1:DateStart><d2p1:Description>Sample and taste all of the best local Utah Craft Beers while tasting Bavarian Inspired Foods and treats

Sample beers from Bohemian Brewery, Uinta Brewing, Squatters Beers, Wasatch Beers, Red Rock Brewery, Roosters Brewery, 10 Barrel Brewing Company, Payette Brewing Company and more!

Earl’s Lodge and Patio

No Reservation Required

Price: $2.50 per sampling token

Samples are poured at 6oz. (2) Tokens Required for Heavy Beer sample. (2) Tokens to fill Mug and (3) Tokens to fill mug with Heavy Beer.

Tokens purchased Saturday October 1st can be redeemed on October 2nd.  Tokens have no cash value after October 2nd. Token sales end one hour before close each day.

 

Packages:

Beer Fest Sample Mug with (4) Tokens $30

Beer Fest Sample Mug and (10) Tokens $45

The King of Beer Fest package: A special Mug with 12 tokens, a special King of Beer Fest crown, a T-shirt, and VIP access to the front of the line from specific breweries.  $125 – limited to the first (50) and after 50 we will sell out!

 

Entertainment:

Saturday – Pimps of Joytime, Candy's River House and Pinetop Inferno

Sunday – Leftover Cuties, Dead Winter Carpenters and Hollering Pines

 

SUNDAY, OCTOBER 2 - KING OF BEER FEST COSTUME CONTEST

3:30pm – the winner of ‘King of Beer Fest’ will be announced which will include a 16.17 season pass.  Those ‘King of Beer Fest’ participants are encouraged to dress up and play the part.  Sunday at around 2:00pm someone will tap you on the shoulder and invite you to the King of Beer Fest awards at 3:30 at the front of the main stage.  Questions, Dancing, and stories will be told while the crowd picks the True King of Beer Fest which will include your name on a wall in the Cinnabar, and bragging rights for life.  2nd prize gets a $125 Snowbasin Resort Gift Card.

Stay at Lakeside Resort Properties this weekend and get a free shuttle to and from your condo PLUS 20% off your stay. See lakesideresortproperties.com/beer-fest-2016 for details.

Must be 21 years of age or older with valid ID to consume alcohol.

***No outside food or beverage allowed in the music venue or the lodge. Utah State Law prohibits the possession and consumption of outside alcohol including beer &amp; wine on premise. Bags may be subject to search at the music venue gate and any alcohol or outside food may be confiscated.</d2p1:Description><d2p1:Distance>0</d2p1:Distance><d2p1:Free>false</d2p1:Free><d2p1:HasTime>true</d2p1:HasTime><d2p1:Id>09768f8891094b3d9e5cdde6c9794368</d2p1:Id><d2p1:Images><d2p1:jsImg><d2p1:id>1</d2p1:id><d2p1:url>https://citysparkstorage.blob.core.windows.net/portalimages/portalimages/e0a25e96-703d-44a3-a497-eab943c4bbb5.large.png</d2p1:url></d2p1:jsImg></d2p1:Images><d2p1:IsPromotion>false</d2p1:IsPromotion><d2p1:Labels xmlns:d4p1="http://schemas.microsoft.com/2003/10/Serialization/Arrays"><d4p1:string>FestivalFair</d4p1:string></d2p1:Labels><d2p1:Links><d2p1:jsLink><d2p1:name>Basin Beer Fest</d2p1:name><d2p1:revP>0</d2p1:revP><d2p1:url>https://www.snowbasin.com/events/detail/basin-beer-fest</d2p1:url></d2p1:jsLink></d2p1:Links><d2p1:Media i:nil="true" /><d2p1:MediumImg>https://citysparkstorage.blob.core.windows.net/portalimages/portalimages/e0a25e96-703d-44a3-a497-eab943c4bbb5.medium.png</d2p1:MediumImg><d2p1:Name>Basin Beer Fest</d2p1:Name><d2p1:Occurances i:nil="true" /><d2p1:PId>2816268</d2p1:PId><d2p1:Picked>false</d2p1:Picked><d2p1:PopularityIndex>46</d2p1:PopularityIndex><d2p1:Price>30</d2p1:Price><d2p1:PriceHigh>125</d2p1:PriceHigh><d2p1:PriceText>Three packages available at $30, $45, $125. $2.50 per token.</d2p1:PriceText><d2p1:SmallImg>https://citysparkstorage.blob.core.windows.net/portalimages/portalimages/e0a25e96-703d-44a3-a497-eab943c4bbb5.small.png</d2p1:SmallImg><d2p1:Sponsor i:nil="true" /><d2p1:SubmitPID>404443</d2p1:SubmitPID><d2p1:Tags xmlns:d4p1="http://schemas.microsoft.com/2003/10/Serialization/Arrays"><d4p1:int>10252</d4p1:int><d4p1:int>10270</d4p1:int><d4p1:int>31</d4p1:int><d4p1:int>5</d4p1:int><d4p1:int>75</d4p1:int><d4p1:int>12</d4p1:int></d2p1:Tags><d2p1:Tickets /><d2p1:Venue>Snowbasin</d2p1:Venue><d2p1:Zip>84101</d2p1:Zip><d2p1:ct i:nil="true" /><d2p1:enhance>false</d2p1:enhance><d2p1:latitude>40.760311126708984</d2p1:latitude><d2p1:lm>2016-09-24T00:29:59.354Z</d2p1:lm><d2p1:longitude>-111.88822174072266</d2p1:longitude></d2p1:jsEvent><d2p1:jsEvent><d2p1:Address i:nil="true" /><d2p1:AllDay>false</d2p1:AllDay><d2p1:BiasTags xmlns:d4p1="http://schemas.microsoft.com/2003/10/Serialization/Arrays" i:nil="true" /><d2p1:CityState>Midvale, UT</d2p1:CityState><d2p1:Date>2016-10-01T00:00:00Z</d2p1:Date><d2p1:DateEnd i:nil="true" /><d2p1:DateStart>2016-10-01T12:00:00Z</d2p1:DateStart><d2p1:Description></d2p1:Description><d2p1:Distance>9.6</d2p1:Distance><d2p1:Free>false</d2p1:Free><d2p1:HasTime>true</d2p1:HasTime><d2p1:Id>60bc92bd242548898a28ecfba507dde7</d2p1:Id><d2p1:Images><d2p1:jsImg><d2p1:id>1</d2p1:id><d2p1:url>https://citysparkstorage.blob.core.windows.net/portalimages/portalimages/83a059e7-3f63-4dbe-9f1b-2bde9c1499a8.large.png</d2p1:url></d2p1:jsImg></d2p1:Images><d2p1:IsPromotion>false</d2p1:IsPromotion><d2p1:Labels xmlns:d4p1="http://schemas.microsoft.com/2003/10/Serialization/Arrays" /><d2p1:Links /><d2p1:Media i:nil="true" /><d2p1:MediumImg>https://citysparkstorage.blob.core.windows.net/portalimages/portalimages/83a059e7-3f63-4dbe-9f1b-2bde9c1499a8.medium.png</d2p1:MediumImg><d2p1:Name>Paul Cardall</d2p1:Name><d2p1:Occurances i:nil="true" /><d2p1:PId>2822844</d2p1:PId><d2p1:Picked>false</d2p1:Picked><d2p1:PopularityIndex>4</d2p1:PopularityIndex><d2p1:Price i:nil="true" /><d2p1:PriceHigh i:nil="true" /><d2p1:PriceText i:nil="true" /><d2p1:SmallImg>https://citysparkstorage.blob.core.windows.net/portalimages/portalimages/83a059e7-3f63-4dbe-9f1b-2bde9c1499a8.small.png</d2p1:SmallImg><d2p1:Sponsor i:nil="true" /><d2p1:SubmitPID i:nil="true" /><d2p1:Tags xmlns:d4p1="http://schemas.microsoft.com/2003/10/Serialization/Arrays"><d4p1:int>2</d4p1:int><d4p1:int>17</d4p1:int><d4p1:int>100</d4p1:int></d2p1:Tags><d2p1:Tickets><d2p1:jsLink><d2p1:name>BandsInTown</d2p1:name><d2p1:revP>0</d2p1:revP><d2p1:url>http://www.bandsintown.com/event/12894241/buy_tickets?app_id=CitySpark&amp;came_from=233</d2p1:url></d2p1:jsLink></d2p1:Tickets><d2p1:Venue>Deseret Book (Ft. Union)</d2p1:Venue><d2p1:Zip i:nil="true" /><d2p1:ct i:nil="true" /><d2p1:enhance>false</d2p1:enhance><d2p1:latitude>40.6231841</d2p1:latitude><d2p1:lm>2016-09-26T13:49:01.017Z</d2p1:lm><d2p1:longitude>-111.8624141</d2p1:longitude></d2p1:jsEvent><d2p1:jsEvent><d2p1:Address>3925 E Snowbasin Rd</d2p1:Address><d2p1:AllDay>false</d2p1:AllDay><d2p1:BiasTags xmlns:d4p1="http://schemas.microsoft.com/2003/10/Serialization/Arrays" i:nil="true" /><d2p1:CityState>Huntsville, UT</d2p1:CityState><d2p1:Date>2016-10-01T00:00:00Z</d2p1:Date><d2p1:DateEnd i:nil="true" /><d2p1:DateStart>2016-10-01T12:00:00Z</d2p1:DateStart><d2p1:Description></d2p1:Description><d2p1:Distance>35.1</d2p1:Distance><d2p1:Free>false</d2p1:Free><d2p1:HasTime>true</d2p1:HasTime><d2p1:Id>d63ac15b6f284aceb14abf24b64cac64</d2p1:Id><d2p1:Images><d2p1:jsImg><d2p1:id>1</d2p1:id><d2p1:url>https://citysparkstorage.blob.core.windows.net/portalimages/portalimages/8400b608-f6a0-43e8-8396-ccffa375239b.large.png</d2p1:url></d2p1:jsImg></d2p1:Images><d2p1:IsPromotion>false</d2p1:IsPromotion><d2p1:Labels xmlns:d4p1="http://schemas.microsoft.com/2003/10/Serialization/Arrays" /><d2p1:Links /><d2p1:Media i:nil="true" /><d2p1:MediumImg>https://citysparkstorage.blob.core.windows.net/portalimages/portalimages/8400b608-f6a0-43e8-8396-ccffa375239b.medium.png</d2p1:MediumImg><d2p1:Name>The Pimps of Joytime</d2p1:Name><d2p1:Occurances i:nil="true" /><d2p1:PId>2822869</d2p1:PId><d2p1:Picked>false</d2p1:Picked><d2p1:PopularityIndex>11</d2p1:PopularityIndex><d2p1:Price i:nil="true" /><d2p1:PriceHigh i:nil="true" /><d2p1:PriceText i:nil="true" /><d2p1:SmallImg>https://citysparkstorage.blob.core.windows.net/portalimages/portalimages/8400b608-f6a0-43e8-8396-ccffa375239b.small.png</d2p1:SmallImg><d2p1:Sponsor i:nil="true" /><d2p1:SubmitPID i:nil="true" /><d2p1:Tags xmlns:d4p1="http://schemas.microsoft.com/2003/10/Serialization/Arrays"><d4p1:int>2</d4p1:int><d4p1:int>17</d4p1:int><d4p1:int>100</d4p1:int></d2p1:Tags><d2p1:Tickets><d2p1:jsLink><d2p1:name>BandsInTown</d2p1:name><d2p1:revP>0</d2p1:revP><d2p1:url>http://www.bandsintown.com/event/12875303/buy_tickets?app_id=CitySpark&amp;came_from=233</d2p1:url></d2p1:jsLink></d2p1:Tickets><d2p1:Venue>Snowbasin Ski Resort</d2p1:Venue><d2p1:Zip i:nil="true" /><d2p1:ct i:nil="true" /><d2p1:enhance>false</d2p1:enhance><d2p1:latitude>41.26077</d2p1:latitude><d2p1:lm>2016-09-26T13:50:18.876Z</d2p1:lm><d2p1:longitude>-111.76994</d2p1:longitude></d2p1:jsEvent><d2p1:jsEvent><d2p1:Address>871 N Cornell St</d2p1:Address><d2p1:AllDay>false</d2p1:AllDay><d2p1:BiasTags xmlns:d4p1="http://schemas.microsoft.com/2003/10/Serialization/Arrays" i:nil="true" /><d2p1:CityState>Salt Lake City, UT</d2p1:CityState><d2p1:Date>2016-10-01T00:00:00Z</d2p1:Date><d2p1:DateEnd>2016-10-01T16:00:00Z</d2p1:DateEnd><d2p1:DateStart>2016-10-01T13:00:00Z</d2p1:DateStart><d2p1:Description>Join Wasatch Community Gardens for an open house tour of this community garden!

___

- Tour of the garden

- Garden games

- Kids crafts

- Photo booth

___

For additional questions, contact Chloe Stevens, Outreach AmeriCorps at chloe@wasatchgardens.org or call 801.359.2658.</d2p1:Description><d2p1:Distance>3.1</d2p1:Distance><d2p1:Free>true</d2p1:Free><d2p1:HasTime>true</d2p1:HasTime><d2p1:Id>c2afde28fc624d29a29f3a025a03cd9e</d2p1:Id><d2p1:Images><d2p1:jsImg><d2p1:id>1</d2p1:id><d2p1:url>https://citysparkstorage.blob.core.windows.net/portalimages/portalimages/04bd1536-1d22-419c-a79c-4c500507300a.large.png</d2p1:url></d2p1:jsImg></d2p1:Images><d2p1:IsPromotion>false</d2p1:IsPromotion><d2p1:Labels xmlns:d4p1="http://schemas.microsoft.com/2003/10/Serialization/Arrays" /><d2p1:Links /><d2p1:Media i:nil="true" /><d2p1:MediumImg>https://citysparkstorage.blob.core.windows.net/portalimages/portalimages/04bd1536-1d22-419c-a79c-4c500507300a.medium.png</d2p1:MediumImg><d2p1:Name>Community Garden Open House</d2p1:Name><d2p1:Occurances i:nil="true" /><d2p1:PId>2744501</d2p1:PId><d2p1:Picked>false</d2p1:Picked><d2p1:PopularityIndex>10</d2p1:PopularityIndex><d2p1:Price i:nil="true" /><d2p1:PriceHigh i:nil="true" /><d2p1:PriceText i:nil="true" /><d2p1:SmallImg>https://citysparkstorage.blob.core.windows.net/portalimages/portalimages/04bd1536-1d22-419c-a79c-4c500507300a.small.png</d2p1:SmallImg><d2p1:Sponsor i:nil="true" /><d2p1:SubmitPID>383140</d2p1:SubmitPID><d2p1:Tags xmlns:d4p1="http://schemas.microsoft.com/2003/10/Serialization/Arrays"><d4p1:int>79</d4p1:int><d4p1:int>34</d4p1:int><d4p1:int>10120</d4p1:int><d4p1:int>5</d4p1:int><d4p1:int>11</d4p1:int><d4p1:int>15</d4p1:int></d2p1:Tags><d2p1:Tickets /><d2p1:Venue>Rose Park Community Garden</d2p1:Venue><d2p1:Zip>84101</d2p1:Zip><d2p1:ct><d2p1:email>Chloe@wasatchgardens.org</d2p1:email><d2p1:name>Chloe Stevens</d2p1:name><d2p1:org>Wasatch Community Gardens</d2p1:org><d2p1:phone i:nil="true" /></d2p1:ct><d2p1:enhance>false</d2p1:enhance><d2p1:latitude>40.788254588842392</d2p1:latitude><d2p1:lm>2016-09-01T00:28:47.686Z</d2p1:lm><d2p1:longitude>-111.93465940654278</d2p1:longitude></d2p1:jsEvent><d2p1:jsEvent><d2p1:Address>1060 S Dalton ave</d2p1:Address><d2p1:AllDay>false</d2p1:AllDay><d2p1:BiasTags xmlns:d4p1="http://schemas.microsoft.com/2003/10/Serialization/Arrays" i:nil="true" /><d2p1:CityState>Salt Lake City, UT</d2p1:CityState><d2p1:Date>2016-10-01T00:00:00Z</d2p1:Date><d2p1:DateEnd i:nil="true" /><d2p1:DateStart>2016-10-01T13:00:00Z</d2p1:DateStart><d2p1:Description>Come and enjoy each others company, incredible music by Wilford Prater and the Jordan Youth Choir, and a memorial walk around the gorgeous gardens\.</d2p1:Description><d2p1:Distance>11.4</d2p1:Distance><d2p1:Free>true</d2p1:Free><d2p1:HasTime>true</d2p1:HasTime><d2p1:Id>05b761cc0ddd46d4920906ea5450c0dd</d2p1:Id><d2p1:Images><d2p1:jsImg><d2p1:id>1</d2p1:id><d2p1:url>https://citysparkstorage.blob.core.windows.net/portalimages/portalimages/63800fe5-4467-4a25-ad8c-1b90c2a6225a.large.png</d2p1:url></d2p1:jsImg></d2p1:Images><d2p1:IsPromotion>false</d2p1:IsPromotion><d2p1:Labels xmlns:d4p1="http://schemas.microsoft.com/2003/10/Serialization/Arrays" /><d2p1:Links><d2p1:jsLink><d2p1:name>Share Parents of Utah Walk for Remembrance and Hope</d2p1:name><d2p1:revP>0</d2p1:revP><d2p1:url>http://shareparentsofutah.org</d2p1:url></d2p1:jsLink></d2p1:Links><d2p1:Media i:nil="true" /><d2p1:MediumImg>https://citysparkstorage.blob.core.windows.net/portalimages/portalimages/63800fe5-4467-4a25-ad8c-1b90c2a6225a.medium.png</d2p1:MediumImg><d2p1:Name>Share Parents of Utah Walk for Remembrance and Hope</d2p1:Name><d2p1:Occurances i:nil="true" /><d2p1:PId>2778826</d2p1:PId><d2p1:Picked>false</d2p1:Picked><d2p1:PopularityIndex>7</d2p1:PopularityIndex><d2p1:Price>0</d2p1:Price><d2p1:PriceHigh>0</d2p1:PriceHigh><d2p1:PriceText i:nil="true" /><d2p1:SmallImg>https://citysparkstorage.blob.core.windows.net/portalimages/portalimages/63800fe5-4467-4a25-ad8c-1b90c2a6225a.small.png</d2p1:SmallImg><d2p1:Sponsor i:nil="true" /><d2p1:SubmitPID i:nil="true" /><d2p1:Tags xmlns:d4p1="http://schemas.microsoft.com/2003/10/Serialization/Arrays"><d4p1:int>11</d4p1:int><d4p1:int>10172</d4p1:int><d4p1:int>10120</d4p1:int><d4p1:int>15</d4p1:int><d4p1:int>79</d4p1:int></d2p1:Tags><d2p1:Tickets /><d2p1:Venue>International Peace Gardens</d2p1:Venue><d2p1:Zip>84101</d2p1:Zip><d2p1:ct i:nil="true" /><d2p1:enhance>false</d2p1:enhance><d2p1:latitude>40.702480316162109</d2p1:latitude><d2p1:lm>2016-09-12T22:37:35.027Z</d2p1:lm><d2p1:longitude>-112.09291839599609</d2p1:longitude></d2p1:jsEvent><d2p1:jsEvent><d2p1:Address>833 Clark Lane</d2p1:Address><d2p1:AllDay>false</d2p1:AllDay><d2p1:BiasTags xmlns:d4p1="http://schemas.microsoft.com/2003/10/Serialization/Arrays" i:nil="true" /><d2p1:CityState>Farmington, UT</d2p1:CityState><d2p1:Date>2016-10-01T00:00:00Z</d2p1:Date><d2p1:DateEnd i:nil="true" /><d2p1:DateStart>2016-10-01T13:00:00Z</d2p1:DateStart><d2p1:Description>Discover your future at Station Park\! Join us on Saturday, October 1st from 1\-4PM in Fountain Square to meet with our retailers and learn about new &amp; exciting employment opportunities\!
 
Participating Businesses:
The Baked Bear
HomeGoods
Chick\-fil\-A
Brixton’s
Maurices
MAD Greens
Gap
Justice
Gymboree
Twigs Bistro
Harmons
Northwestern Mutual
Old Navy
And more</d2p1:Description><d2p1:Distance>15.3</d2p1:Distance><d2p1:Free>true</d2p1:Free><d2p1:HasTime>true</d2p1:HasTime><d2p1:Id>1078b932f2ad4c91ad201a049e219276</d2p1:Id><d2p1:Images><d2p1:jsImg><d2p1:id>1</d2p1:id><d2p1:url>https://citysparkstorage.blob.core.windows.net/portalimages/portalimages/e626d742-a6c0-40b3-9154-fc8982980b80.large.png</d2p1:url></d2p1:jsImg></d2p1:Images><d2p1:IsPromotion>false</d2p1:IsPromotion><d2p1:Labels xmlns:d4p1="http://schemas.microsoft.com/2003/10/Serialization/Arrays" /><d2p1:Links><d2p1:jsLink><d2p1:name>ABC4Utah</d2p1:name><d2p1:revP>0</d2p1:revP><d2p1:url>http://www.shopatstationpark.com/eventscalendar/</d2p1:url></d2p1:jsLink></d2p1:Links><d2p1:Media i:nil="true" /><d2p1:MediumImg>https://citysparkstorage.blob.core.windows.net/portalimages/portalimages/e626d742-a6c0-40b3-9154-fc8982980b80.medium.png</d2p1:MediumImg><d2p1:Name>Job Fair</d2p1:Name><d2p1:Occurances i:nil="true" /><d2p1:PId>2820382</d2p1:PId><d2p1:Picked>false</d2p1:Picked><d2p1:PopularityIndex>11</d2p1:PopularityIndex><d2p1:Price>0</d2p1:Price><d2p1:PriceHigh>0</d2p1:PriceHigh><d2p1:PriceText i:nil="true" /><d2p1:SmallImg>https://citysparkstorage.blob.core.windows.net/portalimages/portalimages/e626d742-a6c0-40b3-9154-fc8982980b80.small.png</d2p1:SmallImg><d2p1:Sponsor i:nil="true" /><d2p1:SubmitPID i:nil="true" /><d2p1:Tags xmlns:d4p1="http://schemas.microsoft.com/2003/10/Serialization/Arrays"><d4p1:int>5</d4p1:int><d4p1:int>31</d4p1:int></d2p1:Tags><d2p1:Tickets /><d2p1:Venue>Station Park</d2p1:Venue><d2p1:Zip>84025</d2p1:Zip><d2p1:ct i:nil="true" /><d2p1:enhance>false</d2p1:enhance><d2p1:latitude>40.9820448607</d2p1:latitude><d2p1:lm>2016-09-25T02:28:31.168Z</d2p1:lm><d2p1:longitude>-111.9059691578</d2p1:longitude></d2p1:jsEvent><d2p1:jsEvent><d2p1:Address>2121 McClelland St E</d2p1:Address><d2p1:AllDay>false</d2p1:AllDay><d2p1:BiasTags xmlns:d4p1="http://schemas.microsoft.com/2003/10/Serialization/Arrays" i:nil="true" /><d2p1:CityState>Salt Lake City, UT</d2p1:CityState><d2p1:Date>2016-10-01T00:00:00Z</d2p1:Date><d2p1:DateEnd>2016-10-01T17:00:00Z</d2p1:DateEnd><d2p1:DateStart>2016-10-01T13:00:00Z</d2p1:DateStart><d2p1:Description>Chronic Tacos</d2p1:Description><d2p1:Distance>2.9</d2p1:Distance><d2p1:Free>true</d2p1:Free><d2p1:HasTime>true</d2p1:HasTime><d2p1:Id>681e6f36b92748debd6e0c01fb4148b6</d2p1:Id><d2p1:Images><d2p1:jsImg><d2p1:id>1</d2p1:id><d2p1:url>https://citysparkstorage.blob.core.windows.net/portalimages/portalimages/ddbe7158-96a6-474b-b75b-83f2f1be5207.large.png</d2p1:url></d2p1:jsImg></d2p1:Images><d2p1:IsPromotion>false</d2p1:IsPromotion><d2p1:Labels xmlns:d4p1="http://schemas.microsoft.com/2003/10/Serialization/Arrays" /><d2p1:Links><d2p1:jsLink><d2p1:name>Chronic Tacos Salt Lake City Grand Opening</d2p1:name><d2p1:revP>0</d2p1:revP><d2p1:url>http://www.chronictacos.com/</d2p1:url></d2p1:jsLink></d2p1:Links><d2p1:Media i:nil="true" /><d2p1:MediumImg>https://citysparkstorage.blob.core.windows.net/portalimages/portalimages/ddbe7158-96a6-474b-b75b-83f2f1be5207.medium.png</d2p1:MediumImg><d2p1:Name>Chronic Tacos Salt Lake City Grand Opening</d2p1:Name><d2p1:Occurances i:nil="true" /><d2p1:PId>2835966</d2p1:PId><d2p1:Picked>false</d2p1:Picked><d2p1:PopularityIndex>35</d2p1:PopularityIndex><d2p1:Price i:nil="true" /><d2p1:PriceHigh i:nil="true" /><d2p1:PriceText i:nil="true" /><d2p1:SmallImg>https://citysparkstorage.blob.core.windows.net/portalimages/portalimages/ddbe7158-96a6-474b-b75b-83f2f1be5207.small.png</d2p1:SmallImg><d2p1:Sponsor i:nil="true" /><d2p1:SubmitPID>409053</d2p1:SubmitPID><d2p1:Tags xmlns:d4p1="http://schemas.microsoft.com/2003/10/Serialization/Arrays"><d4p1:int>74</d4p1:int><d4p1:int>12</d4p1:int></d2p1:Tags><d2p1:Tickets /><d2p1:Venue>Chronic Tacos</d2p1:Venue><d2p1:Zip>84101</d2p1:Zip><d2p1:ct><d2p1:email></d2p1:email><d2p1:name i:nil="true" /><d2p1:org>Chronic Tacos Salt Lake City</d2p1:org><d2p1:phone>801-906-8411</d2p1:phone></d2p1:ct><d2p1:enhance>false</d2p1:enhance><d2p1:latitude>40.724552</d2p1:latitude><d2p1:lm>2016-09-28T22:26:03.123Z</d2p1:lm><d2p1:longitude>-111.860954</d2p1:longitude></d2p1:jsEvent><d2p1:jsEvent><d2p1:Address>663 W 100 S</d2p1:Address><d2p1:AllDay>false</d2p1:AllDay><d2p1:BiasTags xmlns:d4p1="http://schemas.microsoft.com/2003/10/Serialization/Arrays" i:nil="true" /><d2p1:CityState>Salt Lake City, UT</d2p1:CityState><d2p1:Date>2016-10-01T00:00:00Z</d2p1:Date><d2p1:DateEnd>2016-10-01T16:00:00Z</d2p1:DateEnd><d2p1:DateStart>2016-10-01T14:00:00Z</d2p1:DateStart><d2p1:Description>Learn Poi, Staff, Double Staff, Eating, and Prop Building!

Lorin has over 12 years of experience as a professional dancer, fire artist and teacher.

___

4 Saturdays: September 17, September 24, October 1, October 8

2pm - 4pm

SLC Arts Hub (663 W. 100 S.)

$80 for the 4-class workshop (practice props included)

All levels are welcome, ages 10 and up. Individual instruction will be given from each student’s current starting point.

___

*Please Note!* A minimum of six (6) students is required in order for this workshop to run.
All participants must register for the entire workshop, no drop-in classes will be available. If the workshop does not run, registration fees will be refunded through PayPal.</d2p1:Description><d2p1:Distance>1.3</d2p1:Distance><d2p1:Free>false</d2p1:Free><d2p1:HasTime>true</d2p1:HasTime><d2p1:Id>f760a15d0e4d478592e309d658bb9b49</d2p1:Id><d2p1:Images><d2p1:jsImg><d2p1:id>1</d2p1:id><d2p1:url>https://citysparkstorage.blob.core.windows.net/portalimages/portalimages/ebf1c707-0fd9-49ed-8025-c3069ff636e2.large.png</d2p1:url></d2p1:jsImg></d2p1:Images><d2p1:IsPromotion>false</d2p1:IsPromotion><d2p1:Labels xmlns:d4p1="http://schemas.microsoft.com/2003/10/Serialization/Arrays" /><d2p1:Links><d2p1:jsLink><d2p1:name>Samba Fogo Fire Spinning Workshop</d2p1:name><d2p1:revP>0</d2p1:revP><d2p1:url>http://sambafogo.com/event/fire-spinning-workshop-2016/</d2p1:url></d2p1:jsLink></d2p1:Links><d2p1:Media i:nil="true" /><d2p1:MediumImg>https://citysparkstorage.blob.core.windows.net/portalimages/portalimages/ebf1c707-0fd9-49ed-8025-c3069ff636e2.medium.png</d2p1:MediumImg><d2p1:Name>Samba Fogo Fire Spinning Workshop</d2p1:Name><d2p1:Occurances i:nil="true" /><d2p1:PId>2691368</d2p1:PId><d2p1:Picked>false</d2p1:Picked><d2p1:PopularityIndex>8</d2p1:PopularityIndex><d2p1:Price>80</d2p1:Price><d2p1:PriceHigh i:nil="true" /><d2p1:PriceText>$80 for the 4-class workshop - practice props included</d2p1:PriceText><d2p1:SmallImg>https://citysparkstorage.blob.core.windows.net/portalimages/portalimages/ebf1c707-0fd9-49ed-8025-c3069ff636e2.small.png</d2p1:SmallImg><d2p1:Sponsor i:nil="true" /><d2p1:SubmitPID>369779</d2p1:SubmitPID><d2p1:Tags xmlns:d4p1="http://schemas.microsoft.com/2003/10/Serialization/Arrays"><d4p1:int>2</d4p1:int><d4p1:int>41</d4p1:int><d4p1:int>7</d4p1:int></d2p1:Tags><d2p1:Tickets><d2p1:jsLink><d2p1:name>Samba Fogo Fire Spinning Workshop</d2p1:name><d2p1:revP>0</d2p1:revP><d2p1:url>http://sambafogo.com/event/fire-spinning-workshop-2016/</d2p1:url></d2p1:jsLink></d2p1:Tickets><d2p1:Venue>Salt Lake City Arts Hub</d2p1:Venue><d2p1:Zip>84101</d2p1:Zip><d2p1:ct><d2p1:email>info@sambafogo.com</d2p1:email><d2p1:name>Lorin</d2p1:name><d2p1:org>Samba Fogo</d2p1:org><d2p1:phone>8015200444</d2p1:phone></d2p1:ct><d2p1:enhance>false</d2p1:enhance><d2p1:latitude>40.766868591308594</d2p1:latitude><d2p1:lm>2016-08-17T02:53:09.343Z</d2p1:lm><d2p1:longitude>-111.91062927246094</d2p1:longitude></d2p1:jsEvent><d2p1:jsEvent><d2p1:Address>300 S. 1400 East</d2p1:Address><d2p1:AllDay>false</d2p1:AllDay><d2p1:BiasTags xmlns:d4p1="http://schemas.microsoft.com/2003/10/Serialization/Arrays" i:nil="true" /><d2p1:CityState>Salt Lake City, UT</d2p1:CityState><d2p1:Date>2016-10-01T00:00:00Z</d2p1:Date><d2p1:DateEnd i:nil="true" /><d2p1:DateStart>2016-10-01T14:00:00Z</d2p1:DateStart><d2p1:Description>Pioneer Theatre Company presents the regional premiere of *The Last Ship*, the semi-autobiographical lyrical musical by the world-renowned musician Sting. Sting wrote the music and lyrics; the book was written by the Tony and Pulitzer Prize-winning writers John Logan and Brian Yorkey. 

The musical will run from September 16 - October 1, 2016. Tickets for the production go on sale to the general public beginning August 31, 2016 at 10 a.m.  
___

PTC's production will be the first since the show's Tony-nominated (Best Original Score) Broadway run in 2014-2015. PTC is the only theatre in the country given the honor of producing the musical that *The New York Times* said features, "a seductive score that ranks among the best composed by a rock or pop figure on Broadway."</d2p1:Description><d2p1:Distance>1.9</d2p1:Distance><d2p1:Free>false</d2p1:Free><d2p1:HasTime>true</d2p1:HasTime><d2p1:Id>40656399a4114f72aa1a0a4c654e2edb</d2p1:Id><d2p1:Images><d2p1:jsImg><d2p1:id>1</d2p1:id><d2p1:url>https://citysparkstorage.blob.core.windows.net/portalimages/portalimages/f2cbb196-6eff-4e2f-a757-d89aec9b391d.large.png</d2p1:url></d2p1:jsImg></d2p1:Images><d2p1:IsPromotion>false</d2p1:IsPromotion><d2p1:Labels xmlns:d4p1="http://schemas.microsoft.com/2003/10/Serialization/Arrays"><d4p1:string>Theater</d4p1:string></d2p1:Labels><d2p1:Links><d2p1:jsLink><d2p1:name>The Last Ship</d2p1:name><d2p1:revP>0</d2p1:revP><d2p1:url>http://www.pioneertheatre.org</d2p1:url></d2p1:jsLink></d2p1:Links><d2p1:Media i:nil="true" /><d2p1:MediumImg>https://citysparkstorage.blob.core.windows.net/portalimages/portalimages/f2cbb196-6eff-4e2f-a757-d89aec9b391d.medium.png</d2p1:MediumImg><d2p1:Name>The Last Ship</d2p1:Name><d2p1:Occurances i:nil="true" /><d2p1:PId>2741784</d2p1:PId><d2p1:Picked>false</d2p1:Picked><d2p1:PopularityIndex>15</d2p1:PopularityIndex><d2p1:Price>40</d2p1:Price><d2p1:PriceHigh>62</d2p1:PriceHigh><d2p1:PriceText i:nil="true" /><d2p1:SmallImg>https://citysparkstorage.blob.core.windows.net/portalimages/portalimages/f2cbb196-6eff-4e2f-a757-d89aec9b391d.small.png</d2p1:SmallImg><d2p1:Sponsor i:nil="true" /><d2p1:SubmitPID>382199</d2p1:SubmitPID><d2p1:Tags xmlns:d4p1="http://schemas.microsoft.com/2003/10/Serialization/Arrays"><d4p1:int>2</d4p1:int><d4p1:int>19</d4p1:int><d4p1:int>118</d4p1:int></d2p1:Tags><d2p1:Tickets /><d2p1:Venue>Pioneer Theater Company</d2p1:Venue><d2p1:Zip>84101</d2p1:Zip><d2p1:ct i:nil="true" /><d2p1:enhance>false</d2p1:enhance><d2p1:latitude>40.761313810944557</d2p1:latitude><d2p1:lm>2016-08-31T15:15:48.471Z</d2p1:lm><d2p1:longitude>-111.85136877000332</d2p1:longitude></d2p1:jsEvent></events><possible>0</possible></GetEventResponse>